sec_search_client/__init__.py
sec_search_client/api_client.py
sec_search_client/configuration.py
sec_search_client/rest.py
sec_search_client/api/__init__.py
sec_search_client/api/category_api.py
sec_search_client/api/classification_api.py
sec_search_client/api/entity_api.py
sec_search_client/api/filing_api.py
sec_search_client/api/symbol_api.py
sec_search_client/models/__init__.py
sec_search_client/models/http_validation_error.py
sec_search_client/models/validation_error.py
test/__init__.py
test/test_category_api.py
test/test_classification_api.py
test/test_entity_api.py
test/test_filing_api.py
test/test_http_validation_error.py
test/test_symbol_api.py
test/test_validation_error.py
sec_search_client-1.0.0.dist-info/METADATA
sec_search_client-1.0.0.dist-info/WHEEL
sec_search_client-1.0.0.dist-info/top_level.txt
sec_search_client-1.0.0.dist-info/RECORD
