Metadata-Version: 2.1
Name: sec-search-client
Version: 1.0.0
Summary: SEC Search API
Home-page: 
Author-email: 
Keywords: Swagger,SEC Search API
Requires-Dist: urllib3 >=1.15
Requires-Dist: six >=1.10
Requires-Dist: certifi
Requires-Dist: python-dateutil
